ont_pybasecall_client_lib.libs/libbasecall_client-11d999c8.so.7.9.8
pybasecall_client_lib/NanoporeCommunityTCs28November2018.pdf
pybasecall_client_lib/THIRD_PARTY_LICENSES
pybasecall_client_lib/__init__.py
pybasecall_client_lib/client_lib.cpython-310-x86_64-linux-gnu.so
pybasecall_client_lib/example.py
pybasecall_client_lib/helper_functions.py
pybasecall_client_lib/pyclient.py
pybasecall_client_lib/test/__init__.py
pybasecall_client_lib/test/test_client.py
pybasecall_client_lib/test/test_conversion_utils.py
pybasecall_client_lib/test/test_pyclient.py
pybasecall_client_lib/test/data/dna/file0.fast5
pybasecall_client_lib/test/data/dna/file1.fast5
pybasecall_client_lib/test/data/dna/file2.fast5
pybasecall_client_lib/test/data/dna/file3.fast5
pybasecall_client_lib/test/data/dna/file4.fast5
pybasecall_client_lib/test/data/dna/file6.pod5
ont_pybasecall_client_lib-7.9.8.dist-info/METADATA
ont_pybasecall_client_lib-7.9.8.dist-info/WHEEL
ont_pybasecall_client_lib-7.9.8.dist-info/top_level.txt
ont_pybasecall_client_lib-7.9.8.dist-info/RECORD
