Metadata-Version: 2.2
Name: ont-pybasecall-client-lib
Version: 7.9.8
Summary: Python bindings for the BasecallClient library.
Home-page: http://www.nanoporetech.com
Author: Oxford Nanopore Technologies plc
Author-email: unknown@unknown.com
Classifier: Development Status :: 5 - Production/Stable
Classifier: Environment :: Console
Classifier: Intended Audience :: Developers
Classifier: Intended Audience :: Science/Research
Classifier: License :: Other/Proprietary License
Classifier: Natural Language :: English
Classifier: Operating System :: POSIX :: Linux
Classifier: Programming Language :: C++
Classifier: Programming Language :: Python :: 3 :: Only
Classifier: Topic :: Scientific/Engineering :: Bio-Informatics
Requires-Dist: numpy<2.0.0
Dynamic: author
Dynamic: author-email
Dynamic: classifier
Dynamic: description
Dynamic: home-page
Dynamic: requires-dist
Dynamic: summary
